[
  {
    "Type": 0,
    "Value": "oneplus.com"
  },
  {
    "Type": 1,
    "Value": ".oneplus.com"
  },
  {
    "Type": 0,
    "Value": "oneplus.cn"
  },
  {
    "Type": 1,
    "Value": ".oneplus.cn"
  },
  {
    "Type": 0,
    "Value": "oneplus.net"
  },
  {
    "Type": 1,
    "Value": ".oneplus.net"
  },
  {
    "Type": 0,
    "Value": "opstatics.com"
  },
  {
    "Type": 1,
    "Value": ".opstatics.com"
  },
  {
    "Type": 0,
    "Value": "oneplusbbs.com"
  },
  {
    "Type": 1,
    "Value": ".oneplusbbs.com"
  },
  {
    "Type": 0,
    "Value": "oneplusmobile.com"
  },
  {
    "Type": 1,
    "Value": ".oneplusmobile.com"
  },
  {
    "Type": 0,
    "Value": "h2os.com"
  },
  {
    "Type": 1,
    "Value": ".h2os.com"
  },
  {
    "Type": 0,
    "Value": "community.oneplus.com"
  }
]
