[
  {
    "Type": 0,
    "Value": "tcloudhw.net"
  },
  {
    "Type": 1,
    "Value": ".tcloudhw.net"
  },
  {
    "Type": 0,
    "Value": "essurl.com"
  },
  {
    "Type": 1,
    "Value": ".essurl.com"
  },
  {
    "Type": 0,
    "Value": "aitransfy.com"
  },
  {
    "Type": 1,
    "Value": ".aitransfy.com"
  },
  {
    "Type": 0,
    "Value": "apaas-zone-test.com"
  },
  {
    "Type": 1,
    "Value": ".apaas-zone-test.com"
  },
  {
    "Type": 0,
    "Value": "apigwtencent.com"
  },
  {
    "Type": 1,
    "Value": ".apigwtencent.com"
  },
  {
    "Type": 0,
    "Value": "bkapigw.com"
  },
  {
    "Type": 1,
    "Value": ".bkapigw.com"
  },
  {
    "Type": 0,
    "Value": "bkapps.com"
  },
  {
    "Type": 1,
    "Value": ".bkapps.com"
  },
  {
    "Type": 0,
    "Value": "bkclouds.cc"
  },
  {
    "Type": 1,
    "Value": ".bkclouds.cc"
  },
  {
    "Type": 0,
    "Value": "bktencent.com"
  },
  {
    "Type": 1,
    "Value": ".bktencent.com"
  },
  {
    "Type": 0,
    "Value": "build9s.io"
  },
  {
    "Type": 1,
    "Value": ".build9s.io"
  },
  {
    "Type": 0,
    "Value": "byodonline.com"
  },
  {
    "Type": 1,
    "Value": ".byodonline.com"
  },
  {
    "Type": 0,
    "Value": "cdn-go.cn"
  },
  {
    "Type": 1,
    "Value": ".cdn-go.cn"
  },
  {
    "Type": 0,
    "Value": "cdndoctor.com"
  },
  {
    "Type": 1,
    "Value": ".cdndoctor.com"
  },
  {
    "Type": 0,
    "Value": "cdngot.com"
  },
  {
    "Type": 1,
    "Value": ".cdngot.com"
  },
  {
    "Type": 0,
    "Value": "cdntip.com"
  },
  {
    "Type": 1,
    "Value": ".cdntip.com"
  },
  {
    "Type": 0,
    "Value": "cdntips.com"
  },
  {
    "Type": 1,
    "Value": ".cdntips.com"
  },
  {
    "Type": 0,
    "Value": "cdntips.net"
  },
  {
    "Type": 1,
    "Value": ".cdntips.net"
  },
  {
    "Type": 0,
    "Value": "cdnv1.cn"
  },
  {
    "Type": 1,
    "Value": ".cdnv1.cn"
  },
  {
    "Type": 0,
    "Value": "cdnv2.cn"
  },
  {
    "Type": 1,
    "Value": ".cdnv2.cn"
  },
  {
    "Type": 0,
    "Value": "cdnv3.cn"
  },
  {
    "Type": 1,
    "Value": ".cdnv3.cn"
  },
  {
    "Type": 0,
    "Value": "cloud-industry-delivery.site"
  },
  {
    "Type": 1,
    "Value": ".cloud-industry-delivery.site"
  },
  {
    "Type": 0,
    "Value": "cloudbase.cn"
  },
  {
    "Type": 1,
    "Value": ".cloudbase.cn"
  },
  {
    "Type": 0,
    "Value": "cloudbase.net"
  },
  {
    "Type": 1,
    "Value": ".cloudbase.net"
  },
  {
    "Type": 0,
    "Value": "cloudidaas.com"
  },
  {
    "Type": 1,
    "Value": ".cloudidaas.com"
  },
  {
    "Type": 0,
    "Value": "cloudsite.vip"
  },
  {
    "Type": 1,
    "Value": ".cloudsite.vip"
  },
  {
    "Type": 0,
    "Value": "cncqcloud.com"
  },
  {
    "Type": 1,
    "Value": ".cncqcloud.com"
  },
  {
    "Type": 0,
    "Value": "computeinit.com"
  },
  {
    "Type": 1,
    "Value": ".computeinit.com"
  },
  {
    "Type": 0,
    "Value": "coolsite.vip"
  },
  {
    "Type": 1,
    "Value": ".coolsite.vip"
  },
  {
    "Type": 0,
    "Value": "dnsv1.com"
  },
  {
    "Type": 1,
    "Value": ".dnsv1.com"
  },
  {
    "Type": 0,
    "Value": "dothework.cn"
  },
  {
    "Type": 1,
    "Value": ".dothework.cn"
  },
  {
    "Type": 0,
    "Value": "ectencent.cn"
  },
  {
    "Type": 1,
    "Value": ".ectencent.cn"
  },
  {
    "Type": 0,
    "Value": "edgeonedy1.com"
  },
  {
    "Type": 1,
    "Value": ".edgeonedy1.com"
  },
  {
    "Type": 0,
    "Value": "acctdns.com"
  },
  {
    "Type": 1,
    "Value": ".acctdns.com"
  },
  {
    "Type": 0,
    "Value": "exmailgz.com"
  },
  {
    "Type": 1,
    "Value": ".exmailgz.com"
  },
  {
    "Type": 0,
    "Value": "fsphere.cn"
  },
  {
    "Type": 1,
    "Value": ".fsphere.cn"
  },
  {
    "Type": 0,
    "Value": "gaapqcloud.com"
  },
  {
    "Type": 1,
    "Value": ".gaapqcloud.com"
  },
  {
    "Type": 0,
    "Value": "gitdrone.cn"
  },
  {
    "Type": 1,
    "Value": ".gitdrone.cn"
  },
  {
    "Type": 0,
    "Value": "gmedev.cn"
  },
  {
    "Type": 1,
    "Value": ".gmedev.cn"
  },
  {
    "Type": 0,
    "Value": "govqcloud.com"
  },
  {
    "Type": 1,
    "Value": ".govqcloud.com"
  },
  {
    "Type": 0,
    "Value": "gsadds.com"
  },
  {
    "Type": 1,
    "Value": ".gsadds.com"
  },
  {
    "Type": 0,
    "Value": "gtm.pub"
  },
  {
    "Type": 1,
    "Value": ".gtm.pub"
  },
  {
    "Type": 0,
    "Value": "hr-welink.com"
  },
  {
    "Type": 1,
    "Value": ".hr-welink.com"
  },
  {
    "Type": 0,
    "Value": "idcgcloudcs.com"
  },
  {
    "Type": 1,
    "Value": ".idcgcloudcs.com"
  },
  {
    "Type": 0,
    "Value": "iemiq.com"
  },
  {
    "Type": 1,
    "Value": ".iemiq.com"
  },
  {
    "Type": 0,
    "Value": "igtm.pub"
  },
  {
    "Type": 1,
    "Value": ".igtm.pub"
  },
  {
    "Type": 0,
    "Value": "isd.com"
  },
  {
    "Type": 1,
    "Value": ".isd.com"
  },
  {
    "Type": 0,
    "Value": "ispqcloud.com"
  },
  {
    "Type": 1,
    "Value": ".ispqcloud.com"
  },
  {
    "Type": 0,
    "Value": "itopsdk.com"
  },
  {
    "Type": 1,
    "Value": ".itopsdk.com"
  },
  {
    "Type": 0,
    "Value": "my-qcloud.com"
  },
  {
    "Type": 1,
    "Value": ".my-qcloud.com"
  },
  {
    "Type": 0,
    "Value": "myelasticsearch.com"
  },
  {
    "Type": 1,
    "Value": ".myelasticsearch.com"
  },
  {
    "Type": 0,
    "Value": "doh.pub"
  },
  {
    "Type": 1,
    "Value": ".doh.pub"
  },
  {
    "Type": 0,
    "Value": "myqcloud.com"
  },
  {
    "Type": 1,
    "Value": ".myqcloud.com"
  },
  {
    "Type": 0,
    "Value": "onexmail.com"
  },
  {
    "Type": 1,
    "Value": ".onexmail.com"
  },
  {
    "Type": 0,
    "Value": "openapp.run"
  },
  {
    "Type": 1,
    "Value": ".openapp.run"
  },
  {
    "Type": 0,
    "Value": "ovscdns.com"
  },
  {
    "Type": 1,
    "Value": ".ovscdns.com"
  },
  {
    "Type": 0,
    "Value": "ovscdns.net"
  },
  {
    "Type": 1,
    "Value": ".ovscdns.net"
  },
  {
    "Type": 0,
    "Value": "pn1waq.com"
  },
  {
    "Type": 1,
    "Value": ".pn1waq.com"
  },
  {
    "Type": 0,
    "Value": "qcloud-edumall.com"
  },
  {
    "Type": 1,
    "Value": ".qcloud-edumall.com"
  },
  {
    "Type": 0,
    "Value": "qcloud.com"
  },
  {
    "Type": 1,
    "Value": ".qcloud.com"
  },
  {
    "Type": 0,
    "Value": "qcloud.la"
  },
  {
    "Type": 1,
    "Value": ".qcloud.la"
  },
  {
    "Type": 0,
    "Value": "qcloudapps.com"
  },
  {
    "Type": 1,
    "Value": ".qcloudapps.com"
  },
  {
    "Type": 0,
    "Value": "qcloudcdn.com"
  },
  {
    "Type": 1,
    "Value": ".qcloudcdn.com"
  },
  {
    "Type": 0,
    "Value": "qcloudcdntest.cn"
  },
  {
    "Type": 1,
    "Value": ".qcloudcdntest.cn"
  },
  {
    "Type": 0,
    "Value": "qcloudclass.com"
  },
  {
    "Type": 1,
    "Value": ".qcloudclass.com"
  },
  {
    "Type": 0,
    "Value": "qcloudcos.cn"
  },
  {
    "Type": 1,
    "Value": ".qcloudcos.cn"
  },
  {
    "Type": 0,
    "Value": "qcloudcos.com"
  },
  {
    "Type": 1,
    "Value": ".qcloudcos.com"
  },
  {
    "Type": 0,
    "Value": "dnsv5.com"
  },
  {
    "Type": 1,
    "Value": ".dnsv5.com"
  },
  {
    "Type": 0,
    "Value": "dnspod.org"
  },
  {
    "Type": 1,
    "Value": ".dnspod.org"
  },
  {
    "Type": 0,
    "Value": "dnsv3.com"
  },
  {
    "Type": 1,
    "Value": ".dnsv3.com"
  },
  {
    "Type": 0,
    "Value": "qclouder.com"
  },
  {
    "Type": 1,
    "Value": ".qclouder.com"
  },
  {
    "Type": 0,
    "Value": "qcloudgme.com"
  },
  {
    "Type": 1,
    "Value": ".qcloudgme.com"
  },
  {
    "Type": 0,
    "Value": "qcloudimg.com"
  },
  {
    "Type": 1,
    "Value": ".qcloudimg.com"
  },
  {
    "Type": 0,
    "Value": "qcloudipv6.com"
  },
  {
    "Type": 1,
    "Value": ".qcloudipv6.com"
  },
  {
    "Type": 0,
    "Value": "qcloudmarket.com"
  },
  {
    "Type": 1,
    "Value": ".qcloudmarket.com"
  },
  {
    "Type": 0,
    "Value": "qcloudns.com"
  },
  {
    "Type": 1,
    "Value": ".qcloudns.com"
  },
  {
    "Type": 0,
    "Value": "qcloudsmartiot.com"
  },
  {
    "Type": 1,
    "Value": ".qcloudsmartiot.com"
  },
  {
    "Type": 0,
    "Value": "qcloudtcic.com"
  },
  {
    "Type": 1,
    "Value": ".qcloudtcic.com"
  },
  {
    "Type": 0,
    "Value": "qcloudtiw.com"
  },
  {
    "Type": 1,
    "Value": ".qcloudtiw.com"
  },
  {
    "Type": 0,
    "Value": "qcloudtrip.com"
  },
  {
    "Type": 1,
    "Value": ".qcloudtrip.com"
  },
  {
    "Type": 0,
    "Value": "qcloudtt.com"
  },
  {
    "Type": 1,
    "Value": ".qcloudtt.com"
  },
  {
    "Type": 0,
    "Value": "qcloudwaf.com"
  },
  {
    "Type": 1,
    "Value": ".qcloudwaf.com"
  },
  {
    "Type": 0,
    "Value": "qdwebim.com"
  },
  {
    "Type": 1,
    "Value": ".qdwebim.com"
  },
  {
    "Type": 0,
    "Value": "qeodns.com"
  },
  {
    "Type": 1,
    "Value": ".qeodns.com"
  },
  {
    "Type": 0,
    "Value": "qeodns.net"
  },
  {
    "Type": 1,
    "Value": ".qeodns.net"
  },
  {
    "Type": 0,
    "Value": "qqmra.cn"
  },
  {
    "Type": 1,
    "Value": ".qqmra.cn"
  },
  {
    "Type": 0,
    "Value": "qqmra.com"
  },
  {
    "Type": 1,
    "Value": ".qqmra.com"
  },
  {
    "Type": 0,
    "Value": "qyunapp.com"
  },
  {
    "Type": 1,
    "Value": ".qyunapp.com"
  },
  {
    "Type": 0,
    "Value": "serverlesscloud.cn"
  },
  {
    "Type": 1,
    "Value": ".serverlesscloud.cn"
  },
  {
    "Type": 0,
    "Value": "smtcdns.com"
  },
  {
    "Type": 1,
    "Value": ".smtcdns.com"
  },
  {
    "Type": 0,
    "Value": "smtcdns.net"
  },
  {
    "Type": 1,
    "Value": ".smtcdns.net"
  },
  {
    "Type": 0,
    "Value": "spcdntip.com"
  },
  {
    "Type": 1,
    "Value": ".spcdntip.com"
  },
  {
    "Type": 0,
    "Value": "spcdntipbak.com"
  },
  {
    "Type": 1,
    "Value": ".spcdntipbak.com"
  },
  {
    "Type": 0,
    "Value": "spcloudhw.com"
  },
  {
    "Type": 1,
    "Value": ".spcloudhw.com"
  },
  {
    "Type": 0,
    "Value": "spcloudhw.net"
  },
  {
    "Type": 1,
    "Value": ".spcloudhw.net"
  },
  {
    "Type": 0,
    "Value": "srmkp.cn"
  },
  {
    "Type": 1,
    "Value": ".srmkp.cn"
  },
  {
    "Type": 0,
    "Value": "starlakelab.com"
  },
  {
    "Type": 1,
    "Value": ".starlakelab.com"
  },
  {
    "Type": 0,
    "Value": "tamaegis.com"
  },
  {
    "Type": 1,
    "Value": ".tamaegis.com"
  },
  {
    "Type": 0,
    "Value": "tapd.cn"
  },
  {
    "Type": 1,
    "Value": ".tapd.cn"
  },
  {
    "Type": 0,
    "Value": "tcdlive.com"
  },
  {
    "Type": 1,
    "Value": ".tcdlive.com"
  },
  {
    "Type": 0,
    "Value": "tcdnhw.com"
  },
  {
    "Type": 1,
    "Value": ".tcdnhw.com"
  },
  {
    "Type": 0,
    "Value": "tcdnkcbak.com"
  },
  {
    "Type": 1,
    "Value": ".tcdnkcbak.com"
  },
  {
    "Type": 0,
    "Value": "tcdnlive.com"
  },
  {
    "Type": 1,
    "Value": ".tcdnlive.com"
  },
  {
    "Type": 0,
    "Value": "tcdnlivebak1.com"
  },
  {
    "Type": 1,
    "Value": ".tcdnlivebak1.com"
  },
  {
    "Type": 0,
    "Value": "tcdnlivebak2.com"
  },
  {
    "Type": 1,
    "Value": ".tcdnlivebak2.com"
  },
  {
    "Type": 0,
    "Value": "tcdnos.com"
  },
  {
    "Type": 1,
    "Value": ".tcdnos.com"
  },
  {
    "Type": 0,
    "Value": "tcdnos.net"
  },
  {
    "Type": 1,
    "Value": ".tcdnos.net"
  },
  {
    "Type": 0,
    "Value": "tcdntip.com"
  },
  {
    "Type": 1,
    "Value": ".tcdntip.com"
  },
  {
    "Type": 0,
    "Value": "tcdnvod.com"
  },
  {
    "Type": 1,
    "Value": ".tcdnvod.com"
  },
  {
    "Type": 0,
    "Value": "tcdnvodbak.com"
  },
  {
    "Type": 1,
    "Value": ".tcdnvodbak.com"
  },
  {
    "Type": 0,
    "Value": "tcloudbase.com"
  },
  {
    "Type": 1,
    "Value": ".tcloudbase.com"
  },
  {
    "Type": 0,
    "Value": "tcloudbase.net"
  },
  {
    "Type": 1,
    "Value": ".tcloudbase.net"
  },
  {
    "Type": 0,
    "Value": "tcloudbaseapp.com"
  },
  {
    "Type": 1,
    "Value": ".tcloudbaseapp.com"
  },
  {
    "Type": 0,
    "Value": "tcloudbi.com"
  },
  {
    "Type": 1,
    "Value": ".tcloudbi.com"
  },
  {
    "Type": 0,
    "Value": "tclouddrive.com"
  },
  {
    "Type": 1,
    "Value": ".tclouddrive.com"
  },
  {
    "Type": 0,
    "Value": "dnsv4.com"
  },
  {
    "Type": 1,
    "Value": ".dnsv4.com"
  },
  {
    "Type": 0,
    "Value": "tcloudscdn.net"
  },
  {
    "Type": 1,
    "Value": ".tcloudscdn.net"
  },
  {
    "Type": 0,
    "Value": "acctdns.net"
  },
  {
    "Type": 1,
    "Value": ".acctdns.net"
  },
  {
    "Type": 0,
    "Value": "tcloudscdn.com"
  },
  {
    "Type": 1,
    "Value": ".tcloudscdn.com"
  },
  {
    "Type": 0,
    "Value": "tcloudhw.com"
  },
  {
    "Type": 1,
    "Value": ".tcloudhw.com"
  },
  {
    "Type": 0,
    "Value": "tdnsx1.com"
  },
  {
    "Type": 1,
    "Value": ".tdnsx1.com"
  },
  {
    "Type": 0,
    "Value": "techo.chat"
  },
  {
    "Type": 1,
    "Value": ".techo.chat"
  },
  {
    "Type": 0,
    "Value": "tefscloud.com"
  },
  {
    "Type": 1,
    "Value": ".tefscloud.com"
  },
  {
    "Type": 0,
    "Value": "tefscloud.net"
  },
  {
    "Type": 1,
    "Value": ".tefscloud.net"
  },
  {
    "Type": 0,
    "Value": "tenant-zone-dev.com"
  },
  {
    "Type": 1,
    "Value": ".tenant-zone-dev.com"
  },
  {
    "Type": 0,
    "Value": "tencdns.net"
  },
  {
    "Type": 1,
    "Value": ".tencdns.net"
  },
  {
    "Type": 0,
    "Value": "tencent-cloud.com"
  },
  {
    "Type": 1,
    "Value": ".tencent-cloud.com"
  },
  {
    "Type": 0,
    "Value": "tencent-cloud.net"
  },
  {
    "Type": 1,
    "Value": ".tencent-cloud.net"
  },
  {
    "Type": 0,
    "Value": "tencentapps.com"
  },
  {
    "Type": 1,
    "Value": ".tencentapps.com"
  },
  {
    "Type": 0,
    "Value": "tencentbyod.com"
  },
  {
    "Type": 1,
    "Value": ".tencentbyod.com"
  },
  {
    "Type": 0,
    "Value": "tencentcdb.cn"
  },
  {
    "Type": 1,
    "Value": ".tencentcdb.cn"
  },
  {
    "Type": 0,
    "Value": "tencentcdb.com"
  },
  {
    "Type": 1,
    "Value": ".tencentcdb.com"
  },
  {
    "Type": 0,
    "Value": "dns.pub"
  },
  {
    "Type": 1,
    "Value": ".dns.pub"
  },
  {
    "Type": 0,
    "Value": "tencentclb.com"
  },
  {
    "Type": 1,
    "Value": ".tencentclb.com"
  },
  {
    "Type": 0,
    "Value": "tencentcloud-aiot.com"
  },
  {
    "Type": 1,
    "Value": ".tencentcloud-aiot.com"
  },
  {
    "Type": 0,
    "Value": "tencentcloudapi.com"
  },
  {
    "Type": 1,
    "Value": ".tencentcloudapi.com"
  },
  {
    "Type": 0,
    "Value": "tencentcloudclub.com"
  },
  {
    "Type": 1,
    "Value": ".tencentcloudclub.com"
  },
  {
    "Type": 0,
    "Value": "tencentcloudcr.com"
  },
  {
    "Type": 1,
    "Value": ".tencentcloudcr.com"
  },
  {
    "Type": 0,
    "Value": "tencentcloudmarket.com"
  },
  {
    "Type": 1,
    "Value": ".tencentcloudmarket.com"
  },
  {
    "Type": 0,
    "Value": "tencentcloudns.com"
  },
  {
    "Type": 1,
    "Value": ".tencentcloudns.com"
  },
  {
    "Type": 0,
    "Value": "tencentcloudsec.com"
  },
  {
    "Type": 1,
    "Value": ".tencentcloudsec.com"
  },
  {
    "Type": 0,
    "Value": "tencentcloudses.com"
  },
  {
    "Type": 1,
    "Value": ".tencentcloudses.com"
  },
  {
    "Type": 0,
    "Value": "tencentcos.cn"
  },
  {
    "Type": 1,
    "Value": ".tencentcos.cn"
  },
  {
    "Type": 0,
    "Value": "tencentcos.com"
  },
  {
    "Type": 1,
    "Value": ".tencentcos.com"
  },
  {
    "Type": 0,
    "Value": "dnsapi.cn"
  },
  {
    "Type": 1,
    "Value": ".dnsapi.cn"
  },
  {
    "Type": 0,
    "Value": "tencentcs.com"
  },
  {
    "Type": 1,
    "Value": ".tencentcs.com"
  },
  {
    "Type": 0,
    "Value": "tencentdayu.com"
  },
  {
    "Type": 1,
    "Value": ".tencentdayu.com"
  },
  {
    "Type": 0,
    "Value": "tencentdb.com"
  },
  {
    "Type": 1,
    "Value": ".tencentdb.com"
  },
  {
    "Type": 0,
    "Value": "tencentdevices.com"
  },
  {
    "Type": 1,
    "Value": ".tencentdevices.com"
  },
  {
    "Type": 0,
    "Value": "tencentdigitalassistant.com"
  },
  {
    "Type": 1,
    "Value": ".tencentdigitalassistant.com"
  },
  {
    "Type": 0,
    "Value": "tencentdms.com"
  },
  {
    "Type": 1,
    "Value": ".tencentdms.com"
  },
  {
    "Type": 0,
    "Value": "tencenteiam.com"
  },
  {
    "Type": 1,
    "Value": ".tencenteiam.com"
  },
  {
    "Type": 0,
    "Value": "tencentelasticsearch.com"
  },
  {
    "Type": 1,
    "Value": ".tencentelasticsearch.com"
  },
  {
    "Type": 0,
    "Value": "tencentid.com"
  },
  {
    "Type": 1,
    "Value": ".tencentid.com"
  },
  {
    "Type": 0,
    "Value": "tencentidentity.com"
  },
  {
    "Type": 1,
    "Value": ".tencentidentity.com"
  },
  {
    "Type": 0,
    "Value": "tencentproxy.com"
  },
  {
    "Type": 1,
    "Value": ".tencentproxy.com"
  },
  {
    "Type": 0,
    "Value": "tencentrio.com"
  },
  {
    "Type": 1,
    "Value": ".tencentrio.com"
  },
  {
    "Type": 0,
    "Value": "tencenttid.com"
  },
  {
    "Type": 1,
    "Value": ".tencenttid.com"
  },
  {
    "Type": 0,
    "Value": "tencentwemeet.club"
  },
  {
    "Type": 1,
    "Value": ".tencentwemeet.club"
  },
  {
    "Type": 0,
    "Value": "tencentwepark.com"
  },
  {
    "Type": 1,
    "Value": ".tencentwepark.com"
  },
  {
    "Type": 0,
    "Value": "tencentyun.com"
  },
  {
    "Type": 1,
    "Value": ".tencentyun.com"
  },
  {
    "Type": 0,
    "Value": "tendbcluster.com"
  },
  {
    "Type": 1,
    "Value": ".tendbcluster.com"
  },
  {
    "Type": 0,
    "Value": "tendis.net"
  },
  {
    "Type": 1,
    "Value": ".tendis.net"
  },
  {
    "Type": 0,
    "Value": "dnspod.mobi"
  },
  {
    "Type": 1,
    "Value": ".dnspod.mobi"
  },
  {
    "Type": 0,
    "Value": "testmeet.cn"
  },
  {
    "Type": 1,
    "Value": ".testmeet.cn"
  },
  {
    "Type": 0,
    "Value": "testwaf.com"
  },
  {
    "Type": 1,
    "Value": ".testwaf.com"
  },
  {
    "Type": 0,
    "Value": "tgovcloud.com"
  },
  {
    "Type": 1,
    "Value": ".tgovcloud.com"
  },
  {
    "Type": 0,
    "Value": "tidaas.com"
  },
  {
    "Type": 1,
    "Value": ".tidaas.com"
  },
  {
    "Type": 0,
    "Value": "dot.pub"
  },
  {
    "Type": 1,
    "Value": ".dot.pub"
  },
  {
    "Type": 0,
    "Value": "timmerse.com"
  },
  {
    "Type": 1,
    "Value": ".timmerse.com"
  },
  {
    "Type": 0,
    "Value": "tlivecdn.com"
  },
  {
    "Type": 1,
    "Value": ".tlivecdn.com"
  },
  {
    "Type": 0,
    "Value": "tlivepush.com"
  },
  {
    "Type": 1,
    "Value": ".tlivepush.com"
  },
  {
    "Type": 0,
    "Value": "tlivesource.com"
  },
  {
    "Type": 1,
    "Value": ".tlivesource.com"
  },
  {
    "Type": 0,
    "Value": "tourismshow.cn"
  },
  {
    "Type": 1,
    "Value": ".tourismshow.cn"
  },
  {
    "Type": 0,
    "Value": "tourismuser.cn"
  },
  {
    "Type": 1,
    "Value": ".tourismuser.cn"
  },
  {
    "Type": 0,
    "Value": "tsparkling.com"
  },
  {
    "Type": 1,
    "Value": ".tsparkling.com"
  },
  {
    "Type": 0,
    "Value": "tx-exhibition.com"
  },
  {
    "Type": 1,
    "Value": ".tx-exhibition.com"
  },
  {
    "Type": 0,
    "Value": "txbyod.com"
  },
  {
    "Type": 1,
    "Value": ".txbyod.com"
  },
  {
    "Type": 0,
    "Value": "txidc.wang"
  },
  {
    "Type": 1,
    "Value": ".txidc.wang"
  },
  {
    "Type": 0,
    "Value": "txlivecdn.com"
  },
  {
    "Type": 1,
    "Value": ".txlivecdn.com"
  },
  {
    "Type": 0,
    "Value": "txtyxg.com"
  },
  {
    "Type": 1,
    "Value": ".txtyxg.com"
  },
  {
    "Type": 0,
    "Value": "txyscdn.com"
  },
  {
    "Type": 1,
    "Value": ".txyscdn.com"
  },
  {
    "Type": 0,
    "Value": "txyscdn.net"
  },
  {
    "Type": 1,
    "Value": ".txyscdn.net"
  },
  {
    "Type": 0,
    "Value": "uncnn.cn"
  },
  {
    "Type": 1,
    "Value": ".uncnn.cn"
  },
  {
    "Type": 0,
    "Value": "vcloudstc.com"
  },
  {
    "Type": 1,
    "Value": ".vcloudstc.com"
  },
  {
    "Type": 0,
    "Value": "vcloudstc.net"
  },
  {
    "Type": 1,
    "Value": ".vcloudstc.net"
  },
  {
    "Type": 0,
    "Value": "vcloudvod.com"
  },
  {
    "Type": 1,
    "Value": ".vcloudvod.com"
  },
  {
    "Type": 0,
    "Value": "vodtcbk.com"
  },
  {
    "Type": 1,
    "Value": ".vodtcbk.com"
  },
  {
    "Type": 0,
    "Value": "vxo7tu.com"
  },
  {
    "Type": 1,
    "Value": ".vxo7tu.com"
  },
  {
    "Type": 0,
    "Value": "wework-studio.com"
  },
  {
    "Type": 1,
    "Value": ".wework-studio.com"
  },
  {
    "Type": 0,
    "Value": "xqymuy.com"
  },
  {
    "Type": 1,
    "Value": ".xqymuy.com"
  },
  {
    "Type": 0,
    "Value": "yufuid.com"
  },
  {
    "Type": 1,
    "Value": ".yufuid.com"
  },
  {
    "Type": 0,
    "Value": "dnspod.com"
  },
  {
    "Type": 1,
    "Value": ".dnspod.com"
  },
  {
    "Type": 0,
    "Value": "yufuid.net"
  },
  {
    "Type": 1,
    "Value": ".yufuid.net"
  },
  {
    "Type": 0,
    "Value": "yunjitele.com"
  },
  {
    "Type": 1,
    "Value": ".yunjitele.com"
  },
  {
    "Type": 0,
    "Value": "dnspod.cn"
  },
  {
    "Type": 1,
    "Value": ".dnspod.cn"
  },
  {
    "Type": 0,
    "Value": "dnsv2.com"
  },
  {
    "Type": 1,
    "Value": ".dnsv2.com"
  },
  {
    "Type": 0,
    "Value": "dnspod.net"
  },
  {
    "Type": 1,
    "Value": ".dnspod.net"
  },
  {
    "Type": 0,
    "Value": "discuz.org"
  },
  {
    "Type": 1,
    "Value": ".discuz.org"
  },
  {
    "Type": 0,
    "Value": "discuz.net"
  },
  {
    "Type": 1,
    "Value": ".discuz.net"
  },
  {
    "Type": 0,
    "Value": "comsenz.com"
  },
  {
    "Type": 1,
    "Value": ".comsenz.com"
  },
  {
    "Type": 0,
    "Value": "ym.run"
  },
  {
    "Type": 1,
    "Value": ".ym.run"
  },
  {
    "Type": 0,
    "Value": "um.run"
  },
  {
    "Type": 1,
    "Value": ".um.run"
  },
  {
    "Type": 0,
    "Value": "tcloudedu.com"
  },
  {
    "Type": 1,
    "Value": ".tcloudedu.com"
  },
  {
    "Type": 0,
    "Value": "ma.run"
  },
  {
    "Type": 1,
    "Value": ".ma.run"
  },
  {
    "Type": 0,
    "Value": "oracle-tencent.cn"
  },
  {
    "Type": 1,
    "Value": ".oracle-tencent.cn"
  },
  {
    "Type": 0,
    "Value": "oracle-tencent.com"
  },
  {
    "Type": 1,
    "Value": ".oracle-tencent.com"
  },
  {
    "Type": 0,
    "Value": "m9.run"
  },
  {
    "Type": 1,
    "Value": ".m9.run"
  },
  {
    "Type": 0,
    "Value": "oracle-tencent.net"
  },
  {
    "Type": 1,
    "Value": ".oracle-tencent.net"
  },
  {
    "Type": 0,
    "Value": "m6.run"
  },
  {
    "Type": 1,
    "Value": ".m6.run"
  },
  {
    "Type": 0,
    "Value": "m1.run"
  },
  {
    "Type": 1,
    "Value": ".m1.run"
  },
  {
    "Type": 0,
    "Value": "tencentcdb.com.cn"
  },
  {
    "Type": 1,
    "Value": ".tencentcdb.com.cn"
  },
  {
    "Type": 0,
    "Value": "oracle-tencent.com.cn"
  },
  {
    "Type": 1,
    "Value": ".oracle-tencent.com.cn"
  },
  {
    "Type": 0,
    "Value": "dnspod.com.cn"
  },
  {
    "Type": 1,
    "Value": ".dnspod.com.cn"
  },
  {
    "Type": 0,
    "Value": "dnsv1.com.cn"
  },
  {
    "Type": 1,
    "Value": ".dnsv1.com.cn"
  },
  {
    "Type": 0,
    "Value": "ectencent.com.cn"
  },
  {
    "Type": 1,
    "Value": ".ectencent.com.cn"
  },
  {
    "Type": 0,
    "Value": "timatrix.com.cn"
  },
  {
    "Type": 1,
    "Value": ".timatrix.com.cn"
  },
  {
    "Type": 0,
    "Value": "qcloudcos.com.cn"
  },
  {
    "Type": 1,
    "Value": ".qcloudcos.com.cn"
  },
  {
    "Type": 0,
    "Value": "yufuid.com.cn"
  },
  {
    "Type": 1,
    "Value": ".yufuid.com.cn"
  },
  {
    "Type": 0,
    "Value": "testjrzk.net.cn"
  },
  {
    "Type": 1,
    "Value": ".testjrzk.net.cn"
  },
  {
    "Type": 0,
    "Value": "tencentcos.com.cn"
  },
  {
    "Type": 1,
    "Value": ".tencentcos.com.cn"
  },
  {
    "Type": 0,
    "Value": "oracle-tencent.net.cn"
  },
  {
    "Type": 1,
    "Value": ".oracle-tencent.net.cn"
  },
  {
    "Type": 0,
    "Value": "jrzk.net.cn"
  },
  {
    "Type": 1,
    "Value": ".jrzk.net.cn"
  },
  {
    "Type": 3,
    "Value": ".+\\.dnse[0-5]\\.(cn|com)$"
  },
  {
    "Type": 3,
    "Value": ".+\\.tdnsv([1-9]|1[0-5])\\.(com|net)$"
  },
  {
    "Type": 3,
    "Value": "\\.(.+-)?ap-beijing(-.+)?\\.myqcloud\\.com$"
  },
  {
    "Type": 3,
    "Value": "\\.(.+-)?ap-nanjing(-.+)?\\.myqcloud\\.com$"
  },
  {
    "Type": 3,
    "Value": "\\.(.+-)?ap-shanghai(-.+)?\\.myqcloud\\.com$"
  },
  {
    "Type": 3,
    "Value": "\\.(.+-)?ap-guangzhou(-.+)?\\.myqcloud\\.com$"
  },
  {
    "Type": 3,
    "Value": "\\.(.+-)?ap-chengdu(-.+)?\\.myqcloud\\.com$"
  },
  {
    "Type": 3,
    "Value": "\\.(.+-)?ap-chongqing(-.+)?\\.myqcloud\\.com$"
  },
  {
    "Type": 3,
    "Value": "\\.(.+-)?ap-shenzhen(-.+)?\\.myqcloud\\.com$"
  },
  {
    "Type": 3,
    "Value": "\\.(.+-)?ap-beijing(-.+)?\\.tencentcos\\.(cn|com(\\.cn)?)$"
  },
  {
    "Type": 3,
    "Value": "\\.(.+-)?ap-nanjing(-.+)?\\.tencentcos\\.(cn|com(\\.cn)?)$"
  },
  {
    "Type": 3,
    "Value": "\\.(.+-)?ap-shanghai(-.+)?\\.tencentcos\\.(cn|com(\\.cn)?)$"
  },
  {
    "Type": 3,
    "Value": "\\.(.+-)?ap-guangzhou(-.+)?\\.tencentcos\\.(cn|com(\\.cn)?)$"
  },
  {
    "Type": 3,
    "Value": "\\.(.+-)?ap-chengdu(-.+)?\\.tencentcos\\.(cn|com(\\.cn)?)$"
  },
  {
    "Type": 3,
    "Value": "\\.(.+-)?ap-chongqing(-.+)?\\.tencentcos\\.(cn|com(\\.cn)?)$"
  },
  {
    "Type": 3,
    "Value": "\\.(.+-)?ap-shenzhen(-.+)?\\.tencentcos\\.(cn|com(\\.cn)?)$"
  },
  {
    "Type": 0,
    "Value": "intltencentcos.com"
  },
  {
    "Type": 1,
    "Value": ".intltencentcos.com"
  },
  {
    "Type": 0,
    "Value": "ap-hongkong.myqcloud.com"
  },
  {
    "Type": 1,
    "Value": ".ap-hongkong.myqcloud.com"
  },
  {
    "Type": 0,
    "Value": "ap-singapore.myqcloud.com"
  },
  {
    "Type": 1,
    "Value": ".ap-singapore.myqcloud.com"
  },
  {
    "Type": 0,
    "Value": "ap-mumbai.myqcloud.com"
  },
  {
    "Type": 1,
    "Value": ".ap-mumbai.myqcloud.com"
  },
  {
    "Type": 0,
    "Value": "ap-jakarta.myqcloud.com"
  },
  {
    "Type": 1,
    "Value": ".ap-jakarta.myqcloud.com"
  },
  {
    "Type": 0,
    "Value": "ap-seoul.myqcloud.com"
  },
  {
    "Type": 1,
    "Value": ".ap-seoul.myqcloud.com"
  },
  {
    "Type": 0,
    "Value": "ap-bangkok.myqcloud.com"
  },
  {
    "Type": 1,
    "Value": ".ap-bangkok.myqcloud.com"
  },
  {
    "Type": 0,
    "Value": "ap-tokyo.myqcloud.com"
  },
  {
    "Type": 1,
    "Value": ".ap-tokyo.myqcloud.com"
  },
  {
    "Type": 0,
    "Value": "na-siliconvalley.myqcloud.com"
  },
  {
    "Type": 1,
    "Value": ".na-siliconvalley.myqcloud.com"
  },
  {
    "Type": 0,
    "Value": "na-ashburn.myqcloud.com"
  },
  {
    "Type": 1,
    "Value": ".na-ashburn.myqcloud.com"
  },
  {
    "Type": 0,
    "Value": "na-toronto.myqcloud.com"
  },
  {
    "Type": 1,
    "Value": ".na-toronto.myqcloud.com"
  },
  {
    "Type": 0,
    "Value": "sa-saopaulo.myqcloud.com"
  },
  {
    "Type": 1,
    "Value": ".sa-saopaulo.myqcloud.com"
  },
  {
    "Type": 0,
    "Value": "eu-frankfurt.myqcloud.com"
  },
  {
    "Type": 1,
    "Value": ".eu-frankfurt.myqcloud.com"
  },
  {
    "Type": 0,
    "Value": "eu-moscow.myqcloud.com"
  },
  {
    "Type": 1,
    "Value": ".eu-moscow.myqcloud.com"
  },
  {
    "Type": 3,
    "Value": ".+\\.ap-hongkong\\.tencentcos\\.(cn|com(\\.cn)?)$"
  },
  {
    "Type": 3,
    "Value": ".+\\.ap-singapore\\.tencentcos\\.(cn|com(\\.cn)?)$"
  },
  {
    "Type": 3,
    "Value": ".+\\.ap-mumbai\\.tencentcos\\.(cn|com(\\.cn)?)$"
  },
  {
    "Type": 3,
    "Value": ".+\\.ap-jakarta\\.tencentcos\\.(cn|com(\\.cn)?)$"
  },
  {
    "Type": 3,
    "Value": ".+\\.ap-seoul\\.tencentcos\\.(cn|com(\\.cn)?)$"
  },
  {
    "Type": 3,
    "Value": ".+\\.ap-bangkok\\.tencentcos\\.(cn|com(\\.cn)?)$"
  },
  {
    "Type": 3,
    "Value": ".+\\.ap-tokyo\\.tencentcos\\.(cn|com(\\.cn)?)$"
  },
  {
    "Type": 3,
    "Value": ".+\\.na-siliconvalley\\.tencentcos\\.(cn|com(\\.cn)?)$"
  },
  {
    "Type": 3,
    "Value": ".+\\.na-ashburn\\.tencentcos\\.(cn|com(\\.cn)?)$"
  },
  {
    "Type": 3,
    "Value": ".+\\.na-toronto\\.tencentcos\\.(cn|com(\\.cn)?)$"
  },
  {
    "Type": 3,
    "Value": ".+\\.sa-saopaulo\\.tencentcos\\.(cn|com(\\.cn)?)$"
  },
  {
    "Type": 3,
    "Value": ".+\\.eu-frankfurt\\.tencentcos\\.(cn|com(\\.cn)?)$"
  },
  {
    "Type": 3,
    "Value": ".+\\.eu-moscow\\.tencentcos\\.(cn|com(\\.cn)?)$"
  },
  {
    "Type": 0,
    "Value": "coshk.myqcloud.com"
  },
  {
    "Type": 1,
    "Value": ".coshk.myqcloud.com"
  },
  {
    "Type": 0,
    "Value": "cossgp.myqcloud.com"
  },
  {
    "Type": 1,
    "Value": ".cossgp.myqcloud.com"
  },
  {
    "Type": 0,
    "Value": "cosca.myqcloud.com"
  },
  {
    "Type": 1,
    "Value": ".cosca.myqcloud.com"
  },
  {
    "Type": 0,
    "Value": "cosger.myqcloud.com"
  },
  {
    "Type": 1,
    "Value": ".cosger.myqcloud.com"
  },
  {
    "Type": 0,
    "Value": "hk.file.myqcloud.com"
  },
  {
    "Type": 1,
    "Value": ".hk.file.myqcloud.com"
  },
  {
    "Type": 0,
    "Value": "sgp.file.myqcloud.com"
  },
  {
    "Type": 1,
    "Value": ".sgp.file.myqcloud.com"
  },
  {
    "Type": 0,
    "Value": "ca.file.myqcloud.com"
  },
  {
    "Type": 1,
    "Value": ".ca.file.myqcloud.com"
  },
  {
    "Type": 0,
    "Value": "ger.file.myqcloud.com"
  },
  {
    "Type": 1,
    "Value": ".ger.file.myqcloud.com"
  }
]
