[
  {
    "Type": 0,
    "Value": "vfsco.com.cn"
  },
  {
    "Type": 1,
    "Value": ".vfsco.com.cn"
  },
  {
    "Type": 0,
    "Value": "volvo.cn"
  },
  {
    "Type": 1,
    "Value": ".volvo.cn"
  },
  {
    "Type": 0,
    "Value": "volvo.com.cn"
  },
  {
    "Type": 1,
    "Value": ".volvo.com.cn"
  },
  {
    "Type": 0,
    "Value": "volvogroup.cn"
  },
  {
    "Type": 1,
    "Value": ".volvogroup.cn"
  },
  {
    "Type": 0,
    "Value": "volvogroup.com.cn"
  },
  {
    "Type": 1,
    "Value": ".volvogroup.com.cn"
  },
  {
    "Type": 0,
    "Value": "volvotrucks.com.cn"
  },
  {
    "Type": 1,
    "Value": ".volvotrucks.com.cn"
  }
]
